fairkit_learn-1.9.data/scripts/fairkit_learn
fklearn/__init__.py
fklearn/datasets.py
fklearn/fair_model_selection.py
fklearn/fair_selection_aif.py
fklearn/metric_library.py
fklearn/ml_pipeline.py
fklearn/sample.py
fklearn/sample_aif.py
fklearn/scikit_learn_wrapper.py
fklearn/interface/__init__.py
fklearn/interface/main.py
fklearn/interface/plot.py
fklearn/interface/static/css/styles-notebook.css
fklearn/interface/static/data/explanations.json
fairkit_learn-1.9.dist-info/LICENSE
fairkit_learn-1.9.dist-info/METADATA
fairkit_learn-1.9.dist-info/WHEEL
fairkit_learn-1.9.dist-info/top_level.txt
fairkit_learn-1.9.dist-info/RECORD
