Metadata-Version: 2.1
Name: fairkit-learn
Version: 1.9
Summary: A machine learning fairness toolkit
Home-page: https://github.com/brittjay0104/fairkit-learn
Author: Brittany Johnson, Jesse Bartola, Rico Angell, Katherine Keith, Sam Witty, Stephen Giguere, and Yuriy Brun
Author-email: bijohnsonphd@gmail.com
License: UNKNOWN
Platform: UNKNOWN
Classifier: Programming Language :: Python :: 3
Classifier: License :: OSI Approved :: MIT License
Classifier: Operating System :: OS Independent
